{"wordlevel": [{"source": 0, "target": 2, "value": 1, "offsource": 0.0, "offtarget": 0.0, "dwellsource": 413, "dwelltarget": 191, "pupilsource": 364, "pupiltarget": 392, "CURRENT_SAC_AMPLITUDE": 1.58, "CURRENT_SAC_ANGLE": 4.17, "CURRENT_SAC_AVG_VELOCITY": 65.99, "CURRENT_SAC_DIRECTION": "RIGHT", "CURRENT_SAC_DURATION": 24.0, "CURRENT_SAC_PEAK_VELOCITY": 105.25}, {"source": 2, "target": 2, "value": 1, "offsource": 0.0, "offtarget": 0.0, "dwellsource": 191, "dwelltarget": 173, "pupilsource": 392, "pupiltarget": 373, "CURRENT_SAC_AMPLITUDE": 1.6, "CURRENT_SAC_ANGLE": -2.73, "CURRENT_SAC_AVG_VELOCITY": 44.58, "CURRENT_SAC_DIRECTION": "RIGHT", "CURRENT_SAC_DURATION": 36.0, "CURRENT_SAC_PEAK_VELOCITY": 67.86}, {"source": 2, "target": 3, "value": 1, "offsource": 0.0, "offtarget": 0.0, "dwellsource": 173, "dwelltarget": 280, "pupilsource": 373, "pupiltarget": 365, "CURRENT_SAC_AMPLITUDE": 3.02, "CURRENT_SAC_ANGLE": 1.7, "CURRENT_SAC_AVG_VELOCITY": 83.93, "CURRENT_SAC_DIRECTION": "RIGHT", "CURRENT_SAC_DURATION": 36.0, "CURRENT_SAC_PEAK_VELOCITY": 155.42}, {"source": 3, "target": 21, "value": 1, "offsource": 0.0, "offtarget": 0.0, "dwellsource": 280, "dwelltarget": 73, "pupilsource": 365, "pupiltarget": 368, "CURRENT_SAC_AMPLITUDE": 6.02, "CURRENT_SAC_ANGLE": 178.89, "CURRENT_SAC_AVG_VELOCITY": 120.42, "CURRENT_SAC_DIRECTION": "LEFT", "CURRENT_SAC_DURATION": 50.0, "CURRENT_SAC_PEAK_VELOCITY": 249.22}, {"source": 21, "target": 5, "value": 1, "offsource": 0.0, "offtarget": 0.0, "dwellsource": 73, "dwelltarget": 286, "pupilsource": 368, "pupiltarget": 387, "CURRENT_SAC_AMPLITUDE": 4.11, "CURRENT_SAC_ANGLE": -2.11, "CURRENT_SAC_AVG_VELOCITY": 77.6, "CURRENT_SAC_DIRECTION": "RIGHT", "CURRENT_SAC_DURATION": 53.0, "CURRENT_SAC_PEAK_VELOCITY": 191.22}, {"source": 5, "target": 2, "value": 1, "offsource": 0.0, "offtarget": 0.0, "dwellsource": 286, "dwelltarget": 468, "pupilsource": 387, "pupiltarget": 412, "CURRENT_SAC_AMPLITUDE": 1.87, "CURRENT_SAC_ANGLE": 4.47, "CURRENT_SAC_AVG_VELOCITY": 69.08, "CURRENT_SAC_DIRECTION": "RIGHT", "CURRENT_SAC_DURATION": 27.0, "CURRENT_SAC_PEAK_VELOCITY": 116.53}, {"source": 2, "target": 21, "value": 1, "offsource": 0.0, "offtarget": 0.0, "dwellsource": 468, "dwelltarget": 210, "pupilsource": 412, "pupiltarget": 405, "CURRENT_SAC_AMPLITUDE": 3.23, "CURRENT_SAC_ANGLE": -3.17, "CURRENT_SAC_AVG_VELOCITY": 73.32, "CURRENT_SAC_DIRECTION": "RIGHT", "CURRENT_SAC_DURATION": 44.0, "CURRENT_SAC_PEAK_VELOCITY": 199.12}, {"source": 21, "target": 22, "value": 1, "offsource": 0.0, "offtarget": 0.0, "dwellsource": 210, "dwelltarget": 186, "pupilsource": 405, "pupiltarget": 419, "CURRENT_SAC_AMPLITUDE": 3.28, "CURRENT_SAC_ANGLE": -1.55, "CURRENT_SAC_AVG_VELOCITY": 88.64, "CURRENT_SAC_DIRECTION": "RIGHT", "CURRENT_SAC_DURATION": 37.0, "CURRENT_SAC_PEAK_VELOCITY": 167.13}, {"source": 22, "target": 24, "value": 1, "offsource": 0.0, "offtarget": 0.0, "dwellsource": 186, "dwelltarget": 590, "pupilsource": 419, "pupiltarget": 426, "CURRENT_SAC_AMPLITUDE": 2.41, "CURRENT_SAC_ANGLE": 0.08, "CURRENT_SAC_AVG_VELOCITY": 80.25, "CURRENT_SAC_DIRECTION": "RIGHT", "CURRENT_SAC_DURATION": 30.0, "CURRENT_SAC_PEAK_VELOCITY": 132.17}, {"source": 24, "target": 26, "value": 1, "offsource": 0.0, "offtarget": -38.26, "dwellsource": 590, "dwelltarget": 230, "pupilsource": 426, "pupiltarget": 432, "CURRENT_SAC_AMPLITUDE": 2.31, "CURRENT_SAC_ANGLE": -1.88, "CURRENT_SAC_AVG_VELOCITY": 88.97, "CURRENT_SAC_DIRECTION": "RIGHT", "CURRENT_SAC_DURATION": 26.0, "CURRENT_SAC_PEAK_VELOCITY": 142.79}, {"source": 26, "target": 27, "value": 1, "offsource": -38.26, "offtarget": -6.32, "dwellsource": 230, "dwelltarget": 494, "pupilsource": 432, "pupiltarget": 404, "CURRENT_SAC_AMPLITUDE": 3.25, "CURRENT_SAC_ANGLE": 0.78, "CURRENT_SAC_AVG_VELOCITY": 92.84, "CURRENT_SAC_DIRECTION": "RIGHT", "CURRENT_SAC_DURATION": 35.0, "CURRENT_SAC_PEAK_VELOCITY": 157.96}, {"source": 27, "target": 29, "value": 1, "offsource": -6.32, "offtarget": -72.76, "dwellsource": 494, "dwelltarget": 179, "pupilsource": 404, "pupiltarget": 369, "CURRENT_SAC_AMPLITUDE": 4.6, "CURRENT_SAC_ANGLE": 0.27, "CURRENT_SAC_AVG_VELOCITY": 112.19, "CURRENT_SAC_DIRECTION": "RIGHT", "CURRENT_SAC_DURATION": 41.0, "CURRENT_SAC_PEAK_VELOCITY": 166.39}, {"source": 29, "target": 30, "value": 1, "offsource": -72.76, "offtarget": 0.0, "dwellsource": 179, "dwelltarget": 270, "pupilsource": 369, "pupiltarget": 354, "CURRENT_SAC_AMPLITUDE": 1.55, "CURRENT_SAC_ANGLE": 4.07, "CURRENT_SAC_AVG_VELOCITY": 57.35, "CURRENT_SAC_DIRECTION": "RIGHT", "CURRENT_SAC_DURATION": 27.0, "CURRENT_SAC_PEAK_VELOCITY": 87.52}, {"source": 30, "target": 33, "value": 1, "offsource": 0.0, "offtarget": -82.62, "dwellsource": 270, "dwelltarget": 211, "pupilsource": 354, "pupiltarget": 342, "CURRENT_SAC_AMPLITUDE": 3.35, "CURRENT_SAC_ANGLE": 7.63, "CURRENT_SAC_AVG_VELOCITY": 77.8, "CURRENT_SAC_DIRECTION": "RIGHT", "CURRENT_SAC_DURATION": 43.0, "CURRENT_SAC_PEAK_VELOCITY": 110.85}, {"source": 33, "target": 33, "value": 1, "offsource": -82.62, "offtarget": 1.9, "dwellsource": 211, "dwelltarget": 313, "pupilsource": 342, "pupiltarget": 335, "CURRENT_SAC_AMPLITUDE": 1.04, "CURRENT_SAC_ANGLE": 8.16, "CURRENT_SAC_AVG_VELOCITY": 47.25, "CURRENT_SAC_DIRECTION": "RIGHT", "CURRENT_SAC_DURATION": 22.0, "CURRENT_SAC_PEAK_VELOCITY": 69.3}, {"source": 33, "target": 17, "value": 1, "offsource": 1.9, "offtarget": 0.0, "dwellsource": 313, "dwelltarget": 347, "pupilsource": 335, "pupiltarget": 330, "CURRENT_SAC_AMPLITUDE": 29.31, "CURRENT_SAC_ANGLE": -178.38, "CURRENT_SAC_AVG_VELOCITY": 254.89, "CURRENT_SAC_DIRECTION": "LEFT", "CURRENT_SAC_DURATION": 115.0, "CURRENT_SAC_PEAK_VELOCITY": 401.05}, {"source": 17, "target": 35, "value": 1, "offsource": 0.0, "offtarget": 0.0, "dwellsource": 347, "dwelltarget": 326, "pupilsource": 330, "pupiltarget": 349, "CURRENT_SAC_AMPLITUDE": 3.83, "CURRENT_SAC_ANGLE": -2.1, "CURRENT_SAC_AVG_VELOCITY": 91.23, "CURRENT_SAC_DIRECTION": "RIGHT", "CURRENT_SAC_DURATION": 42.0, "CURRENT_SAC_PEAK_VELOCITY": 129.69}, {"source": 35, "target": 20, "value": 1, "offsource": 0.0, "offtarget": 0.0, "dwellsource": 326, "dwelltarget": 284, "pupilsource": 349, "pupiltarget": 409, "CURRENT_SAC_AMPLITUDE": 3.79, "CURRENT_SAC_ANGLE": 177.06, "CURRENT_SAC_AVG_VELOCITY": 71.55, "CURRENT_SAC_DIRECTION": "LEFT", "CURRENT_SAC_DURATION": 53.0, "CURRENT_SAC_PEAK_VELOCITY": 162.28}, {"source": 20, "target": 21, "value": 1, "offsource": 0.0, "offtarget": 0.0, "dwellsource": 284, "dwelltarget": 241, "pupilsource": 409, "pupiltarget": 376, "CURRENT_SAC_AMPLITUDE": 6.16, "CURRENT_SAC_ANGLE": -1.43, "CURRENT_SAC_AVG_VELOCITY": 110.03, "CURRENT_SAC_DIRECTION": "RIGHT", "CURRENT_SAC_DURATION": 56.0, "CURRENT_SAC_PEAK_VELOCITY": 265.05}, {"source": 21, "target": 20, "value": 1, "offsource": 0.0, "offtarget": -62.41, "dwellsource": 241, "dwelltarget": 254, "pupilsource": 376, "pupiltarget": 386, "CURRENT_SAC_AMPLITUDE": 2.15, "CURRENT_SAC_ANGLE": -2.48, "CURRENT_SAC_AVG_VELOCITY": 82.57, "CURRENT_SAC_DIRECTION": "RIGHT", "CURRENT_SAC_DURATION": 26.0, "CURRENT_SAC_PEAK_VELOCITY": 144.89}, {"source": 20, "target": 41, "value": 1, "offsource": -62.41, "offtarget": 0.0, "dwellsource": 254, "dwelltarget": 147, "pupilsource": 386, "pupiltarget": 405, "CURRENT_SAC_AMPLITUDE": 2.95, "CURRENT_SAC_ANGLE": -0.12, "CURRENT_SAC_AVG_VELOCITY": 77.56, "CURRENT_SAC_DIRECTION": "RIGHT", "CURRENT_SAC_DURATION": 38.0, "CURRENT_SAC_PEAK_VELOCITY": 146.65}, {"source": 41, "target": 42, "value": 1, "offsource": 0.0, "offtarget": 0.0, "dwellsource": 147, "dwelltarget": 165, "pupilsource": 405, "pupiltarget": 415, "CURRENT_SAC_AMPLITUDE": 2.3, "CURRENT_SAC_ANGLE": -1.96, "CURRENT_SAC_AVG_VELOCITY": 82.31, "CURRENT_SAC_DIRECTION": "RIGHT", "CURRENT_SAC_DURATION": 28.0, "CURRENT_SAC_PEAK_VELOCITY": 138.04}, {"source": 42, "target": 24, "value": 1, "offsource": 0.0, "offtarget": 0.0, "dwellsource": 165, "dwelltarget": 196, "pupilsource": 415, "pupiltarget": 415, "CURRENT_SAC_AMPLITUDE": 3.46, "CURRENT_SAC_ANGLE": -1.63, "CURRENT_SAC_AVG_VELOCITY": 91.0, "CURRENT_SAC_DIRECTION": "RIGHT", "CURRENT_SAC_DURATION": 38.0, "CURRENT_SAC_PEAK_VELOCITY": 131.79}, {"source": 24, "target": 26, "value": 1, "offsource": 0.0, "offtarget": 0.0, "dwellsource": 196, "dwelltarget": 320, "pupilsource": 415, "pupiltarget": 398, "CURRENT_SAC_AMPLITUDE": 3.08, "CURRENT_SAC_ANGLE": -2.82, "CURRENT_SAC_AVG_VELOCITY": 79.07, "CURRENT_SAC_DIRECTION": "RIGHT", "CURRENT_SAC_DURATION": 39.0, "CURRENT_SAC_PEAK_VELOCITY": 175.76}, {"source": 26, "target": 27, "value": 1, "offsource": 0.0, "offtarget": 0.0, "dwellsource": 320, "dwelltarget": 141, "pupilsource": 398, "pupiltarget": 381, "CURRENT_SAC_AMPLITUDE": 4.57, "CURRENT_SAC_ANGLE": 6.85, "CURRENT_SAC_AVG_VELOCITY": 111.43, "CURRENT_SAC_DIRECTION": "RIGHT", "CURRENT_SAC_DURATION": 41.0, "CURRENT_SAC_PEAK_VELOCITY": 212.97}, {"source": 27, "target": 47, "value": 1, "offsource": 0.0, "offtarget": -37.91, "dwellsource": 141, "dwelltarget": 187, "pupilsource": 381, "pupiltarget": 382, "CURRENT_SAC_AMPLITUDE": 3.43, "CURRENT_SAC_ANGLE": -3.35, "CURRENT_SAC_AVG_VELOCITY": 85.67, "CURRENT_SAC_DIRECTION": "RIGHT", "CURRENT_SAC_DURATION": 40.0, "CURRENT_SAC_PEAK_VELOCITY": 153.27}, {"source": 47, "target": 31, "value": 1, "offsource": -37.91, "offtarget": 0.0, "dwellsource": 187, "dwelltarget": 270, "pupilsource": 382, "pupiltarget": 395, "CURRENT_SAC_AMPLITUDE": 3.38, "CURRENT_SAC_ANGLE": -0.2, "CURRENT_SAC_AVG_VELOCITY": 96.69, "CURRENT_SAC_DIRECTION": "RIGHT", "CURRENT_SAC_DURATION": 35.0, "CURRENT_SAC_PEAK_VELOCITY": 139.5}, {"source": 31, "target": 50, "value": 1, "offsource": 0.0, "offtarget": 0.0, "dwellsource": 270, "dwelltarget": 355, "pupilsource": 395, "pupiltarget": 395, "CURRENT_SAC_AMPLITUDE": 1.09, "CURRENT_SAC_ANGLE": -1.71, "CURRENT_SAC_AVG_VELOCITY": 47.24, "CURRENT_SAC_DIRECTION": "RIGHT", "CURRENT_SAC_DURATION": 23.0, "CURRENT_SAC_PEAK_VELOCITY": 76.29}, {"source": 50, "target": 34, "value": 1, "offsource": 0.0, "offtarget": 0.0, "dwellsource": 355, "dwelltarget": 319, "pupilsource": 395, "pupiltarget": 356, "CURRENT_SAC_AMPLITUDE": 29.32, "CURRENT_SAC_ANGLE": -178.8, "CURRENT_SAC_AVG_VELOCITY": 274.05, "CURRENT_SAC_DIRECTION": "LEFT", "CURRENT_SAC_DURATION": 107.0, "CURRENT_SAC_PEAK_VELOCITY": 430.54}, {"source": 34, "target": 53, "value": 1, "offsource": 0.0, "offtarget": 0.0, "dwellsource": 319, "dwelltarget": 200, "pupilsource": 356, "pupiltarget": 357, "CURRENT_SAC_AMPLITUDE": 0.78, "CURRENT_SAC_ANGLE": -171.58, "CURRENT_SAC_AVG_VELOCITY": 20.51, "CURRENT_SAC_DIRECTION": "LEFT", "CURRENT_SAC_DURATION": 38.0, "CURRENT_SAC_PEAK_VELOCITY": 80.33}, {"source": 53, "target": 38, "value": 1, "offsource": 0.0, "offtarget": -96.41, "dwellsource": 200, "dwelltarget": 174, "pupilsource": 357, "pupiltarget": 395, "CURRENT_SAC_AMPLITUDE": 2.59, "CURRENT_SAC_ANGLE": -1.3, "CURRENT_SAC_AVG_VELOCITY": 89.35, "CURRENT_SAC_DIRECTION": "RIGHT", "CURRENT_SAC_DURATION": 29.0, "CURRENT_SAC_PEAK_VELOCITY": 162.28}, {"source": 38, "target": 36, "value": 1, "offsource": -96.41, "offtarget": 0.0, "dwellsource": 174, "dwelltarget": 179, "pupilsource": 395, "pupiltarget": 395, "CURRENT_SAC_AMPLITUDE": 4.58, "CURRENT_SAC_ANGLE": 1.21, "CURRENT_SAC_AVG_VELOCITY": 109.11, "CURRENT_SAC_DIRECTION": "RIGHT", "CURRENT_SAC_DURATION": 42.0, "CURRENT_SAC_PEAK_VELOCITY": 220.48}, {"source": 36, "target": 38, "value": 1, "offsource": 0.0, "offtarget": 0.0, "dwellsource": 179, "dwelltarget": 194, "pupilsource": 395, "pupiltarget": 388, "CURRENT_SAC_AMPLITUDE": 4.74, "CURRENT_SAC_ANGLE": 1.02, "CURRENT_SAC_AVG_VELOCITY": 83.16, "CURRENT_SAC_DIRECTION": "RIGHT", "CURRENT_SAC_DURATION": 57.0, "CURRENT_SAC_PEAK_VELOCITY": 196.04}, {"source": 38, "target": 41, "value": 1, "offsource": 0.0, "offtarget": 0.0, "dwellsource": 194, "dwelltarget": 288, "pupilsource": 388, "pupiltarget": 410, "CURRENT_SAC_AMPLITUDE": 1.43, "CURRENT_SAC_ANGLE": 13.8, "CURRENT_SAC_AVG_VELOCITY": 59.44, "CURRENT_SAC_DIRECTION": "RIGHT", "CURRENT_SAC_DURATION": 24.0, "CURRENT_SAC_PEAK_VELOCITY": 94.59}, {"source": 41, "target": 60, "value": 1, "offsource": 0.0, "offtarget": 0.0, "dwellsource": 288, "dwelltarget": 226, "pupilsource": 410, "pupiltarget": 431, "CURRENT_SAC_AMPLITUDE": 0.12, "CURRENT_SAC_ANGLE": 150.97, "CURRENT_SAC_AVG_VELOCITY": 5.08, "CURRENT_SAC_DIRECTION": ".", "CURRENT_SAC_DURATION": 23.0, "CURRENT_SAC_PEAK_VELOCITY": 33.17}, {"source": 60, "target": 44, "value": 1, "offsource": 0.0, "offtarget": 0.0, "dwellsource": 226, "dwelltarget": 250, "pupilsource": 431, "pupiltarget": 415, "CURRENT_SAC_AMPLITUDE": 4.21, "CURRENT_SAC_ANGLE": -6.22, "CURRENT_SAC_AVG_VELOCITY": 97.88, "CURRENT_SAC_DIRECTION": "RIGHT", "CURRENT_SAC_DURATION": 43.0, "CURRENT_SAC_PEAK_VELOCITY": 199.95}, {"source": 44, "target": 44, "value": 1, "offsource": 0.0, "offtarget": 0.0, "dwellsource": 250, "dwelltarget": 269, "pupilsource": 415, "pupiltarget": 421, "CURRENT_SAC_AMPLITUDE": 5.53, "CURRENT_SAC_ANGLE": -3.01, "CURRENT_SAC_AVG_VELOCITY": 120.26, "CURRENT_SAC_DIRECTION": "RIGHT", "CURRENT_SAC_DURATION": 46.0, "CURRENT_SAC_PEAK_VELOCITY": 264.25}, {"source": 44, "target": 62, "value": 1, "offsource": 0.0, "offtarget": 0.0, "dwellsource": 269, "dwelltarget": 235, "pupilsource": 421, "pupiltarget": 437, "CURRENT_SAC_AMPLITUDE": 4.77, "CURRENT_SAC_ANGLE": 5.84, "CURRENT_SAC_AVG_VELOCITY": 108.45, "CURRENT_SAC_DIRECTION": "RIGHT", "CURRENT_SAC_DURATION": 44.0, "CURRENT_SAC_PEAK_VELOCITY": 189.51}, {"source": 62, "target": 64, "value": 1, "offsource": 0.0, "offtarget": 0.0, "dwellsource": 235, "dwelltarget": 249, "pupilsource": 437, "pupiltarget": 406, "CURRENT_SAC_AMPLITUDE": 1.67, "CURRENT_SAC_ANGLE": 10.16, "CURRENT_SAC_AVG_VELOCITY": 59.58, "CURRENT_SAC_DIRECTION": "RIGHT", "CURRENT_SAC_DURATION": 28.0, "CURRENT_SAC_PEAK_VELOCITY": 97.35}, {"source": 64, "target": 50, "value": 1, "offsource": 0.0, "offtarget": 0.0, "dwellsource": 249, "dwelltarget": 208, "pupilsource": 406, "pupiltarget": 381, "CURRENT_SAC_AMPLITUDE": 2.45, "CURRENT_SAC_ANGLE": 1.35, "CURRENT_SAC_AVG_VELOCITY": 78.99, "CURRENT_SAC_DIRECTION": "RIGHT", "CURRENT_SAC_DURATION": 31.0, "CURRENT_SAC_PEAK_VELOCITY": 132.79}, {"source": 50, "target": 50, "value": 1, "offsource": 0.0, "offtarget": 0.0, "dwellsource": 208, "dwelltarget": 140, "pupilsource": 381, "pupiltarget": 375, "CURRENT_SAC_AMPLITUDE": 1.4, "CURRENT_SAC_ANGLE": -1.83, "CURRENT_SAC_AVG_VELOCITY": 58.22, "CURRENT_SAC_DIRECTION": "RIGHT", "CURRENT_SAC_DURATION": 24.0, "CURRENT_SAC_PEAK_VELOCITY": 83.22}, {"source": 50, "target": 53, "value": 1, "offsource": 0.0, "offtarget": -83.9, "dwellsource": 140, "dwelltarget": 189, "pupilsource": 375, "pupiltarget": 383, "CURRENT_SAC_AMPLITUDE": 2.74, "CURRENT_SAC_ANGLE": 0.37, "CURRENT_SAC_AVG_VELOCITY": 78.42, "CURRENT_SAC_DIRECTION": "RIGHT", "CURRENT_SAC_DURATION": 35.0, "CURRENT_SAC_PEAK_VELOCITY": 136.97}, {"source": 53, "target": 53, "value": 1, "offsource": -83.9, "offtarget": 7.27, "dwellsource": 189, "dwelltarget": 407, "pupilsource": 383, "pupiltarget": 376, "CURRENT_SAC_AMPLITUDE": 28.77, "CURRENT_SAC_ANGLE": -178.41, "CURRENT_SAC_AVG_VELOCITY": 232.03, "CURRENT_SAC_DIRECTION": "LEFT", "CURRENT_SAC_DURATION": 124.0, "CURRENT_SAC_PEAK_VELOCITY": 390.43}, {"source": 53, "target": 54, "value": 1, "offsource": 7.27, "offtarget": 0.0, "dwellsource": 407, "dwelltarget": 133, "pupilsource": 376, "pupiltarget": 377, "CURRENT_SAC_AMPLITUDE": 2.59, "CURRENT_SAC_ANGLE": -178.1, "CURRENT_SAC_AVG_VELOCITY": 47.09, "CURRENT_SAC_DIRECTION": "LEFT", "CURRENT_SAC_DURATION": 55.0, "CURRENT_SAC_PEAK_VELOCITY": 170.67}, {"source": 54, "target": 56, "value": 1, "offsource": 0.0, "offtarget": 71.89, "dwellsource": 133, "dwelltarget": 113, "pupilsource": 377, "pupiltarget": 430, "CURRENT_SAC_AMPLITUDE": 4.95, "CURRENT_SAC_ANGLE": 1.62, "CURRENT_SAC_AVG_VELOCITY": 115.02, "CURRENT_SAC_DIRECTION": "RIGHT", "CURRENT_SAC_DURATION": 43.0, "CURRENT_SAC_PEAK_VELOCITY": 207.01}, {"source": 56, "target": 55, "value": 1, "offsource": 71.89, "offtarget": 0.0, "dwellsource": 113, "dwelltarget": 246, "pupilsource": 430, "pupiltarget": 397, "CURRENT_SAC_AMPLITUDE": 1.61, "CURRENT_SAC_ANGLE": -5.34, "CURRENT_SAC_AVG_VELOCITY": 64.41, "CURRENT_SAC_DIRECTION": "RIGHT", "CURRENT_SAC_DURATION": 25.0, "CURRENT_SAC_PEAK_VELOCITY": 102.11}, {"source": 55, "target": 58, "value": 1, "offsource": 0.0, "offtarget": 0.0, "dwellsource": 246, "dwelltarget": 265, "pupilsource": 397, "pupiltarget": 350, "CURRENT_SAC_AMPLITUDE": 1.74, "CURRENT_SAC_ANGLE": 3.88, "CURRENT_SAC_AVG_VELOCITY": 64.27, "CURRENT_SAC_DIRECTION": "RIGHT", "CURRENT_SAC_DURATION": 27.0, "CURRENT_SAC_PEAK_VELOCITY": 101.1}, {"source": 58, "target": 58, "value": 1, "offsource": 0.0, "offtarget": 0.0, "dwellsource": 265, "dwelltarget": 252, "pupilsource": 350, "pupiltarget": 348, "CURRENT_SAC_AMPLITUDE": 2.74, "CURRENT_SAC_ANGLE": -177.88, "CURRENT_SAC_AVG_VELOCITY": 58.31, "CURRENT_SAC_DIRECTION": "LEFT", "CURRENT_SAC_DURATION": 47.0, "CURRENT_SAC_PEAK_VELOCITY": 157.12}, {"source": 58, "target": 58, "value": 1, "offsource": 0.0, "offtarget": 69.69, "dwellsource": 252, "dwelltarget": 210, "pupilsource": 348, "pupiltarget": 342, "CURRENT_SAC_AMPLITUDE": 5.86, "CURRENT_SAC_ANGLE": -0.27, "CURRENT_SAC_AVG_VELOCITY": 139.61, "CURRENT_SAC_DIRECTION": "RIGHT", "CURRENT_SAC_DURATION": 42.0, "CURRENT_SAC_PEAK_VELOCITY": 256.1}, {"source": 58, "target": 58, "value": 1, "offsource": 69.69, "offtarget": 0.0, "dwellsource": 210, "dwelltarget": 226, "pupilsource": 342, "pupiltarget": 366, "CURRENT_SAC_AMPLITUDE": 5.22, "CURRENT_SAC_ANGLE": -1.45, "CURRENT_SAC_AVG_VELOCITY": 98.58, "CURRENT_SAC_DIRECTION": "RIGHT", "CURRENT_SAC_DURATION": 53.0, "CURRENT_SAC_PEAK_VELOCITY": 245.77}, {"source": 58, "target": 60, "value": 1, "offsource": 0.0, "offtarget": 0.0, "dwellsource": 226, "dwelltarget": 228, "pupilsource": 366, "pupiltarget": 406, "CURRENT_SAC_AMPLITUDE": 3.58, "CURRENT_SAC_ANGLE": -1.57, "CURRENT_SAC_AVG_VELOCITY": 83.22, "CURRENT_SAC_DIRECTION": "RIGHT", "CURRENT_SAC_DURATION": 43.0, "CURRENT_SAC_PEAK_VELOCITY": 161.41}, {"source": 60, "target": 62, "value": 1, "offsource": 0.0, "offtarget": 0.0, "dwellsource": 228, "dwelltarget": 229, "pupilsource": 406, "pupiltarget": 389, "CURRENT_SAC_AMPLITUDE": 4.46, "CURRENT_SAC_ANGLE": 177.32, "CURRENT_SAC_AVG_VELOCITY": 108.89, "CURRENT_SAC_DIRECTION": "LEFT", "CURRENT_SAC_DURATION": 41.0, "CURRENT_SAC_PEAK_VELOCITY": 197.25}, {"source": 62, "target": 64, "value": 1, "offsource": 0.0, "offtarget": 0.0, "dwellsource": 229, "dwelltarget": 221, "pupilsource": 389, "pupiltarget": 384, "CURRENT_SAC_AMPLITUDE": 3.36, "CURRENT_SAC_ANGLE": 0.87, "CURRENT_SAC_AVG_VELOCITY": 74.63, "CURRENT_SAC_DIRECTION": "RIGHT", "CURRENT_SAC_DURATION": 45.0, "CURRENT_SAC_PEAK_VELOCITY": 161.03}, {"source": 64, "target": 61, "value": 1, "offsource": 0.0, "offtarget": 0.0, "dwellsource": 221, "dwelltarget": 293, "pupilsource": 384, "pupiltarget": 403, "CURRENT_SAC_AMPLITUDE": 2.43, "CURRENT_SAC_ANGLE": 1.49, "CURRENT_SAC_AVG_VELOCITY": 86.71, "CURRENT_SAC_DIRECTION": "RIGHT", "CURRENT_SAC_DURATION": 28.0, "CURRENT_SAC_PEAK_VELOCITY": 144.54}, {"source": 61, "target": 63, "value": 1, "offsource": 0.0, "offtarget": 0.0, "dwellsource": 293, "dwelltarget": 219, "pupilsource": 403, "pupiltarget": 411, "CURRENT_SAC_AMPLITUDE": 3.59, "CURRENT_SAC_ANGLE": -3.41, "CURRENT_SAC_AVG_VELOCITY": 92.17, "CURRENT_SAC_DIRECTION": "RIGHT", "CURRENT_SAC_DURATION": 39.0, "CURRENT_SAC_PEAK_VELOCITY": 168.08}, {"source": 63, "target": 64, "value": 1, "offsource": 0.0, "offtarget": 0.0, "dwellsource": 219, "dwelltarget": 237, "pupilsource": 411, "pupiltarget": 383, "CURRENT_SAC_AMPLITUDE": 1.92, "CURRENT_SAC_ANGLE": -4.27, "CURRENT_SAC_AVG_VELOCITY": 49.25, "CURRENT_SAC_DIRECTION": "RIGHT", "CURRENT_SAC_DURATION": 39.0, "CURRENT_SAC_PEAK_VELOCITY": 92.99}, {"source": 64, "target": 66, "value": 1, "offsource": 0.0, "offtarget": 0.0, "dwellsource": 237, "dwelltarget": 218, "pupilsource": 383, "pupiltarget": 350, "CURRENT_SAC_AMPLITUDE": 3.39, "CURRENT_SAC_ANGLE": 5.08, "CURRENT_SAC_AVG_VELOCITY": 91.7, "CURRENT_SAC_DIRECTION": "RIGHT", "CURRENT_SAC_DURATION": 37.0, "CURRENT_SAC_PEAK_VELOCITY": 163.62}, {"source": 66, "target": 81, "value": 1, "offsource": 0.0, "offtarget": 0.0, "dwellsource": 218, "dwelltarget": 212, "pupilsource": 350, "pupiltarget": 337, "CURRENT_SAC_AMPLITUDE": 2.3, "CURRENT_SAC_ANGLE": 4.12, "CURRENT_SAC_AVG_VELOCITY": 71.83, "CURRENT_SAC_DIRECTION": "RIGHT", "CURRENT_SAC_DURATION": 32.0, "CURRENT_SAC_PEAK_VELOCITY": 125.54}, {"source": 81, "target": 68, "value": 1, "offsource": 0.0, "offtarget": 0.0, "dwellsource": 212, "dwelltarget": 299, "pupilsource": 337, "pupiltarget": 336, "CURRENT_SAC_AMPLITUDE": 29.14, "CURRENT_SAC_ANGLE": -177.07, "CURRENT_SAC_AVG_VELOCITY": 274.9, "CURRENT_SAC_DIRECTION": "LEFT", "CURRENT_SAC_DURATION": 106.0, "CURRENT_SAC_PEAK_VELOCITY": 426.22}, {"source": 68, "target": 69, "value": 1, "offsource": 0.0, "offtarget": 0.45, "dwellsource": 299, "dwelltarget": 155, "pupilsource": 336, "pupiltarget": 342, "CURRENT_SAC_AMPLITUDE": 4.36, "CURRENT_SAC_ANGLE": 3.12, "CURRENT_SAC_AVG_VELOCITY": 109.01, "CURRENT_SAC_DIRECTION": "RIGHT", "CURRENT_SAC_DURATION": 40.0, "CURRENT_SAC_PEAK_VELOCITY": 212.72}, {"source": 69, "target": 70, "value": 1, "offsource": 0.45, "offtarget": 0.0, "dwellsource": 155, "dwelltarget": 287, "pupilsource": 342, "pupiltarget": 358, "CURRENT_SAC_AMPLITUDE": 4.01, "CURRENT_SAC_ANGLE": 2.4, "CURRENT_SAC_AVG_VELOCITY": 93.2, "CURRENT_SAC_DIRECTION": "RIGHT", "CURRENT_SAC_DURATION": 43.0, "CURRENT_SAC_PEAK_VELOCITY": 202.01}, {"source": 70, "target": 72, "value": 1, "offsource": 0.0, "offtarget": 0.0, "dwellsource": 287, "dwelltarget": 402, "pupilsource": 358, "pupiltarget": 332, "CURRENT_SAC_AMPLITUDE": 1.3, "CURRENT_SAC_ANGLE": 0.55, "CURRENT_SAC_AVG_VELOCITY": 59.08, "CURRENT_SAC_DIRECTION": "RIGHT", "CURRENT_SAC_DURATION": 22.0, "CURRENT_SAC_PEAK_VELOCITY": 96.09}, {"source": 72, "target": 74, "value": 1, "offsource": 0.0, "offtarget": 29.29, "dwellsource": 402, "dwelltarget": 276, "pupilsource": 332, "pupiltarget": 367, "CURRENT_SAC_AMPLITUDE": 4.22, "CURRENT_SAC_ANGLE": 1.79, "CURRENT_SAC_AVG_VELOCITY": 102.97, "CURRENT_SAC_DIRECTION": "RIGHT", "CURRENT_SAC_DURATION": 41.0, "CURRENT_SAC_PEAK_VELOCITY": 193.81}, {"source": 74, "target": 75, "value": 1, "offsource": 29.29, "offtarget": 0.0, "dwellsource": 276, "dwelltarget": 236, "pupilsource": 367, "pupiltarget": 398, "CURRENT_SAC_AMPLITUDE": 1.89, "CURRENT_SAC_ANGLE": -8.07, "CURRENT_SAC_AVG_VELOCITY": 78.79, "CURRENT_SAC_DIRECTION": "RIGHT", "CURRENT_SAC_DURATION": 24.0, "CURRENT_SAC_PEAK_VELOCITY": 126.51}, {"source": 75, "target": 77, "value": 1, "offsource": 0.0, "offtarget": -52.86, "dwellsource": 236, "dwelltarget": 175, "pupilsource": 398, "pupiltarget": 409, "CURRENT_SAC_AMPLITUDE": 4.63, "CURRENT_SAC_ANGLE": -1.68, "CURRENT_SAC_AVG_VELOCITY": 90.76, "CURRENT_SAC_DIRECTION": "RIGHT", "CURRENT_SAC_DURATION": 51.0, "CURRENT_SAC_PEAK_VELOCITY": 213.06}, {"source": 77, "target": 78, "value": 1, "offsource": -52.86, "offtarget": -16.25, "dwellsource": 175, "dwelltarget": 157, "pupilsource": 409, "pupiltarget": 425, "CURRENT_SAC_AMPLITUDE": 0.84, "CURRENT_SAC_ANGLE": 143.56, "CURRENT_SAC_AVG_VELOCITY": 39.84, "CURRENT_SAC_DIRECTION": "LEFT", "CURRENT_SAC_DURATION": 21.0, "CURRENT_SAC_PEAK_VELOCITY": 62.41}, {"source": 78, "target": 80, "value": 1, "offsource": -16.25, "offtarget": 0.0, "dwellsource": 157, "dwelltarget": 344, "pupilsource": 425, "pupiltarget": 423, "CURRENT_SAC_AMPLITUDE": 5.14, "CURRENT_SAC_ANGLE": -0.6, "CURRENT_SAC_AVG_VELOCITY": 95.12, "CURRENT_SAC_DIRECTION": "RIGHT", "CURRENT_SAC_DURATION": 54.0, "CURRENT_SAC_PEAK_VELOCITY": 190.68}, {"source": 80, "target": 80, "value": 1, "offsource": 0.0, "offtarget": -111.45, "dwellsource": 344, "dwelltarget": 52, "pupilsource": 423, "pupiltarget": 429, "CURRENT_SAC_AMPLITUDE": 2.27, "CURRENT_SAC_ANGLE": 5.02, "CURRENT_SAC_AVG_VELOCITY": 55.37, "CURRENT_SAC_DIRECTION": "RIGHT", "CURRENT_SAC_DURATION": 41.0, "CURRENT_SAC_PEAK_VELOCITY": 103.17}, {"source": 80, "target": 80, "value": 1, "offsource": -111.45, "offtarget": 0.0, "dwellsource": 52, "dwelltarget": 197, "pupilsource": 429, "pupiltarget": 439, "CURRENT_SAC_AMPLITUDE": 3.99, "CURRENT_SAC_ANGLE": 0.83, "CURRENT_SAC_AVG_VELOCITY": 97.38, "CURRENT_SAC_DIRECTION": "RIGHT", "CURRENT_SAC_DURATION": 41.0, "CURRENT_SAC_PEAK_VELOCITY": 168.87}, {"source": 80, "target": 81, "value": 1, "offsource": 0.0, "offtarget": 0.0, "dwellsource": 197, "dwelltarget": 235, "pupilsource": 439, "pupiltarget": 446, "CURRENT_SAC_AMPLITUDE": 1.25, "CURRENT_SAC_ANGLE": 2.48, "CURRENT_SAC_AVG_VELOCITY": 59.42, "CURRENT_SAC_DIRECTION": "RIGHT", "CURRENT_SAC_DURATION": 21.0, "CURRENT_SAC_PEAK_VELOCITY": 81.1}, {"source": 81, "target": 83, "value": 1, "offsource": 0.0, "offtarget": 0.0, "dwellsource": 235, "dwelltarget": 296, "pupilsource": 446, "pupiltarget": 410, "CURRENT_SAC_AMPLITUDE": 1.12, "CURRENT_SAC_ANGLE": -0.3, "CURRENT_SAC_AVG_VELOCITY": 43.11, "CURRENT_SAC_DIRECTION": "RIGHT", "CURRENT_SAC_DURATION": 26.0, "CURRENT_SAC_PEAK_VELOCITY": 69.33}, {"source": 83, "target": 84, "value": 1, "offsource": 0.0, "offtarget": 0.0, "dwellsource": 296, "dwelltarget": 219, "pupilsource": 410, "pupiltarget": 411, "CURRENT_SAC_AMPLITUDE": 28.75, "CURRENT_SAC_ANGLE": -178.62, "CURRENT_SAC_AVG_VELOCITY": 239.56, "CURRENT_SAC_DIRECTION": "LEFT", "CURRENT_SAC_DURATION": 120.0, "CURRENT_SAC_PEAK_VELOCITY": 423.66}, {"source": 84, "target": 84, "value": 1, "offsource": 0.0, "offtarget": 0.0, "dwellsource": 219, "dwelltarget": 296, "pupilsource": 411, "pupiltarget": 415, "CURRENT_SAC_AMPLITUDE": 2.15, "CURRENT_SAC_ANGLE": 10.62, "CURRENT_SAC_AVG_VELOCITY": 79.74, "CURRENT_SAC_DIRECTION": "RIGHT", "CURRENT_SAC_DURATION": 27.0, "CURRENT_SAC_PEAK_VELOCITY": 138.87}, {"source": 84, "target": 87, "value": 1, "offsource": 0.0, "offtarget": -44.14, "dwellsource": 296, "dwelltarget": 277, "pupilsource": 415, "pupiltarget": 443, "CURRENT_SAC_AMPLITUDE": 5.55, "CURRENT_SAC_ANGLE": 0.69, "CURRENT_SAC_AVG_VELOCITY": 126.06, "CURRENT_SAC_DIRECTION": "RIGHT", "CURRENT_SAC_DURATION": 44.0, "CURRENT_SAC_PEAK_VELOCITY": 213.05}, {"source": 87, "target": 88, "value": 1, "offsource": -44.14, "offtarget": -91.67, "dwellsource": 277, "dwelltarget": 389, "pupilsource": 443, "pupiltarget": 397, "CURRENT_SAC_AMPLITUDE": 1.21, "CURRENT_SAC_ANGLE": -179.85, "CURRENT_SAC_AVG_VELOCITY": 46.62, "CURRENT_SAC_DIRECTION": "LEFT", "CURRENT_SAC_DURATION": 26.0, "CURRENT_SAC_PEAK_VELOCITY": 78.05}, {"source": 88, "target": 91, "value": 1, "offsource": -91.67, "offtarget": -0.54, "dwellsource": 389, "dwelltarget": 225, "pupilsource": 397, "pupiltarget": 409, "CURRENT_SAC_AMPLITUDE": 5.11, "CURRENT_SAC_ANGLE": -2.06, "CURRENT_SAC_AVG_VELOCITY": 113.47, "CURRENT_SAC_DIRECTION": "RIGHT", "CURRENT_SAC_DURATION": 45.0, "CURRENT_SAC_PEAK_VELOCITY": 211.9}, {"source": 91, "target": 90, "value": 1, "offsource": -0.54, "offtarget": 53.51, "dwellsource": 225, "dwelltarget": 124, "pupilsource": 409, "pupiltarget": 414, "CURRENT_SAC_AMPLITUDE": 3.65, "CURRENT_SAC_ANGLE": 3.72, "CURRENT_SAC_AVG_VELOCITY": 72.95, "CURRENT_SAC_DIRECTION": "RIGHT", "CURRENT_SAC_DURATION": 50.0, "CURRENT_SAC_PEAK_VELOCITY": 158.82}, {"source": 90, "target": 92, "value": 1, "offsource": 53.51, "offtarget": 18.29, "dwellsource": 124, "dwelltarget": 183, "pupilsource": 414, "pupiltarget": 399, "CURRENT_SAC_AMPLITUDE": 17.6, "CURRENT_SAC_ANGLE": -20.32, "CURRENT_SAC_AVG_VELOCITY": 88.44, "CURRENT_SAC_DIRECTION": "RIGHT", "CURRENT_SAC_DURATION": 199.0, "CURRENT_SAC_PEAK_VELOCITY": 388.12}, {"source": 92, "target": 93, "value": 1, "offsource": 18.29, "offtarget": -27.23, "dwellsource": 183, "dwelltarget": 404, "pupilsource": 399, "pupiltarget": 390, "CURRENT_SAC_AMPLITUDE": 1.38, "CURRENT_SAC_ANGLE": -1.44, "CURRENT_SAC_AVG_VELOCITY": 55.09, "CURRENT_SAC_DIRECTION": "RIGHT", "CURRENT_SAC_DURATION": 25.0, "CURRENT_SAC_PEAK_VELOCITY": 91.83}]}