{"name": "MICROSTORY", "children": [{"name": "Oraci\u00f3n 1", "full": "Oraci\u00f3n 1", "children": [{"name": "Frase 1", "full": "Frase 1", "children": [{"name": "En", "dwell": 0, "id": 0, "pos": "ADP", "len": 2, "freq_abs": 4234281, "freq_norm": 27755.16, "new_line": true, "gaze_time": 0}, {"name": "segundos", "dwell": 603, "id": 1, "pos": "NOUN", "len": 8, "freq_abs": 7969, "freq_norm": 52.23, "gaze_time": 160}, {"name": "todo", "dwell": 393, "id": 2, "pos": "PRON", "len": 4, "freq_abs": 247340, "freq_norm": 1621.28, "gaze_time": 393}, {"name": "fue", "dwell": 189, "id": 3, "pos": "AUX", "len": 3, "freq_abs": 223791, "freq_norm": 1466.92, "gaze_time": 189}, {"name": "un", "dwell": 0, "id": 4, "pos": "DET", "len": 2, "freq_abs": 1659827, "freq_norm": 10879.95, "gaze_time": 0}, {"name": "caos", "dwell": 228, "id": 5, "pos": "NOUN", "len": 4, "freq_abs": 2842, "freq_norm": 18.62, "gaze_time": 228}, {"name": "indescriptible.", "dwell": 589, "id": 6, "pos": "ADJ", "len": 14, "freq_abs": 309, "freq_norm": 2.02, "gaze_time": 589}, {"name": "La", "dwell": 21, "id": 7, "pos": "DET", "len": 2, "freq_abs": 6277560, "freq_norm": 41148.59, "gaze_time": 21}, {"name": "vida", "dwell": 227, "id": 8, "pos": "NOUN", "len": 4, "freq_abs": 123491, "freq_norm": 809.46, "gaze_time": 227}, {"name": "aparentaba", "dwell": 424, "id": 9, "pos": "VERB", "len": 10, "freq_abs": 185, "freq_norm": 1.21, "gaze_time": 424}, {"name": "haber", "dwell": 245, "id": 10, "pos": "AUX", "len": 5, "freq_abs": 54150, "freq_norm": 354.94, "gaze_time": 245}, {"name": "desaparecido.", "dwell": 511, "id": 11, "pos": "VERB", "len": 12, "freq_abs": 4413, "freq_norm": 28.92, "gaze_time": 511}, {"name": "Ella", "dwell": 462, "id": 12, "pos": "PRON", "len": 4, "freq_abs": 110620, "freq_norm": 725.09, "gaze_time": 216}, {"name": "se", "dwell": 513, "id": 13, "pos": "PRON", "len": 2, "freq_abs": 2022514, "freq_norm": 13257.31, "gaze_time": 513}, {"name": "sacudi\u00f3", "dwell": 472, "id": 14, "pos": "VERB", "len": 7, "freq_abs": 819, "freq_norm": 5.36, "break_line": true, "gaze_time": 160}, {"name": "el", "dwell": 0, "id": 15, "pos": "DET", "len": 2, "freq_abs": 4569652, "freq_norm": 29953.48, "new_line": true, "gaze_time": 0}, {"name": "polvo", "dwell": 410, "id": 16, "pos": "NOUN", "len": 5, "freq_abs": 6592, "freq_norm": 43.2, "gaze_time": 181}, {"name": "que", "dwell": 159, "id": 17, "pos": "PRON", "len": 3, "freq_abs": 4681839, "freq_norm": 30688.85, "gaze_time": 159}, {"name": "la", "dwell": 440, "id": 18, "pos": "PRON", "len": 2, "freq_abs": 6277560, "freq_norm": 41148.59, "gaze_time": 440}, {"name": "cubr\u00eda", "dwell": 0, "id": 19, "pos": "VERB", "len": 6, "freq_abs": 1242, "freq_norm": 8.14, "gaze_time": 0}, {"name": "y", "dwell": 0, "id": 20, "pos": "CONJ", "len": 1, "freq_abs": 4180279, "freq_norm": 27401.19, "gaze_time": 0}, {"name": "se", "dwell": 226, "id": 21, "pos": "PRON", "len": 2, "freq_abs": 2022514, "freq_norm": 13257.31, "gaze_time": 226}, {"name": "levant\u00f3", "dwell": 157, "id": 22, "pos": "VERB", "len": 7, "freq_abs": 5695, "freq_norm": 37.32, "gaze_time": 157}, {"name": "de", "dwell": 0, "id": 23, "pos": "ADP", "len": 2, "freq_abs": 9999518, "freq_norm": 65545.55, "gaze_time": 0}, {"name": "entre", "dwell": 218, "id": 24, "pos": "ADP", "len": 5, "freq_abs": 267493, "freq_norm": 1753.38, "gaze_time": 218}, {"name": "las", "dwell": 394, "id": 25, "pos": "DET", "len": 3, "freq_abs": 1686741, "freq_norm": 11056.37, "gaze_time": 394}, {"name": "ruinas:", "dwell": 0, "id": 26, "pos": "NOUN", "len": 7, "freq_abs": 0, "freq_norm": 0.0, "gaze_time": 0}, {"name": "sus", "dwell": 324, "id": 27, "pos": "DET", "len": 3, "freq_abs": 449870, "freq_norm": 2948.84, "gaze_time": 324}, {"name": "ojitos", "dwell": 113, "id": 28, "pos": "NOUN", "len": 6, "freq_abs": 230, "freq_norm": 1.5, "gaze_time": 113}, {"name": "azorados", "dwell": 531, "id": 29, "pos": "ADJ", "len": 8, "freq_abs": 49, "freq_norm": 0.32, "gaze_time": 531}, {"name": "vieron", "dwell": 273, "id": 30, "pos": "VERB", "len": 6, "freq_abs": 4464, "freq_norm": 29.26, "gaze_time": 273}, {"name": "el", "dwell": 0, "id": 31, "pos": "DET", "len": 2, "freq_abs": 4569652, "freq_norm": 29953.48, "gaze_time": 0}, {"name": "espanto.", "dwell": 402, "id": 32, "pos": "NOUN", "len": 7, "freq_abs": 1011, "freq_norm": 6.62, "gaze_time": 402}, {"name": "De", "dwell": 194, "id": 33, "pos": "ADP", "len": 2, "freq_abs": 9999518, "freq_norm": 65545.55, "break_line": true, "gaze_time": 194}, {"name": "pronto", "dwell": 415, "id": 34, "pos": "NOUN", "len": 6, "freq_abs": 26934, "freq_norm": 176.54, "new_line": true, "gaze_time": 415}, {"name": "asom\u00f3", "dwell": 182, "id": 35, "pos": "VERB", "len": 5, "freq_abs": 801, "freq_norm": 5.25, "gaze_time": 182}, {"name": "otra", "dwell": 255, "id": 36, "pos": "DET", "len": 4, "freq_abs": 113982, "freq_norm": 747.13, "gaze_time": 255}, {"name": "cucaracha", "dwell": 611, "id": 37, "pos": "NOUN", "len": 9, "freq_abs": 181, "freq_norm": 1.18, "gaze_time": 611}, {"name": "y", "dwell": 0, "id": 38, "pos": "CONJ", "len": 1, "freq_abs": 4180279, "freq_norm": 27401.19, "gaze_time": 0}, {"name": "juntas", "dwell": 262, "id": 39, "pos": "ADJ", "len": 6, "freq_abs": 3649, "freq_norm": 23.91, "gaze_time": 262}, {"name": "se", "dwell": 0, "id": 40, "pos": "PRON", "len": 2, "freq_abs": 2022514, "freq_norm": 13257.31, "gaze_time": 0}, {"name": "escabulleron", "dwell": 371, "id": 41, "pos": "VERB", "len": 12, "freq_abs": 9, "freq_norm": 0.05, "gaze_time": 371}, {"name": "por", "dwell": 138, "id": 42, "pos": "ADP", "len": 3, "freq_abs": 1561904, "freq_norm": 10238.07, "gaze_time": 138}, {"name": "entre", "dwell": 547, "id": 43, "pos": "ADP", "len": 5, "freq_abs": 267493, "freq_norm": 1753.38, "gaze_time": 173}, {"name": "los", "dwell": 592, "id": 44, "pos": "DET", "len": 3, "freq_abs": 2618657, "freq_norm": 17164.95, "gaze_time": 0}, {"name": "escombros.", "dwell": 264, "id": 45, "pos": "NOUN", "len": 9, "freq_abs": 1095, "freq_norm": 7.17, "gaze_time": 264}]}]}]}